resource_generator/__init__.py
resource_generator/cli_factory.py
resource_generator/controller_command.py
resource_generator/main.py
resource_generator/model_command.py
resource_generator/repository_command.py
resource_generator/schema_command.py
resource_generator/service_command.py
resource_generator-0.1.7.dist-info/LICENSE
resource_generator-0.1.7.dist-info/METADATA
resource_generator-0.1.7.dist-info/WHEEL
resource_generator-0.1.7.dist-info/entry_points.txt
resource_generator-0.1.7.dist-info/RECORD
